LICENSE
MANIFEST.in
README.md
bitvis.ipynb
setup.py
bitjet/__init__.py
bitjet/bitjet.js
bitjet/bitjet.py
bitjet.egg-info/PKG-INFO
bitjet.egg-info/SOURCES.txt
bitjet.egg-info/dependency_links.txt
bitjet.egg-info/pbr.json
bitjet.egg-info/requires.txt
bitjet.egg-info/top_level.txt