Metadata-Version: 1.1
Name: bitjet
Version: 0.2
Summary: Binary visualization using IPython widgets
Home-page: https://github.com/rgbkrk/bitjet
Author: Kyle Kelley
Author-email: rgbkrk@gmail.com
License: New BSD License
Keywords: data visualization interactive interaction python ipython widgets widget
Platform: UNKNOWN
Classifier: Development Status :: 4 - Beta
Classifier: Programming Language :: Python
Classifier: License :: OSI Approved :: MIT License
